netcut/__init__.py
netcut/api_monitor.py
netcut/arp.py
netcut/bandwidth.py
netcut/bluetooth.py
netcut/cdn_detect.py
netcut/check.py
netcut/dhcp.py
netcut/dnsleak.py
netcut/firewall.py
netcut/geo.py
netcut/interfaces.py
netcut/lan_discovery.py
netcut/main.py
netcut/mitm_detect.py
netcut/netifaces_viewer.py
netcut/packets.py
netcut/portscan.py
netcut/protocols.py
netcut/proxy_check.py
netcut/reachability.py
netcut/speedtest_cli.py
netcut/ssl_viewer.py
netcut/stats.py
netcut/statuspage.py
netcut/subdomains.py
netcut/tech_stack.py
netcut/traceroute.py
netcut/tunnel_check.py
netcut/whois_lookup.py
netcut/wifi_heatmap.py
netcut-1.1.dist-info/METADATA
netcut-1.1.dist-info/WHEEL
netcut-1.1.dist-info/entry_points.txt
netcut-1.1.dist-info/top_level.txt
netcut-1.1.dist-info/RECORD
