Metadata-Version: 2.4
Name: netcut
Version: 1.1
Summary: Terminal-based network diagnostics and intelligence toolkit
Author: Shailesh Saravanan
Author-email: Shailesh Saravanan <shaileshsaravanan385@gmail.com>
License-Expression: MIT
Requires-Python: >=3.7
Requires-Dist: requests
Requires-Dist: scapy
Requires-Dist: dnspython
Requires-Dist: psutil
Requires-Dist: beautifulsoup4
Requires-Dist: speedtest-cli
Requires-Dist: python-whois
Requires-Dist: ping3
Requires-Dist: rich
Dynamic: author
Dynamic: requires-python
